.gitignore
README.md
setup.py
isula/__init__.py
isula/client.py
isula/utils.py
isula.egg-info/PKG-INFO
isula.egg-info/SOURCES.txt
isula.egg-info/dependency_links.txt
isula.egg-info/requires.txt
isula.egg-info/top_level.txt
isula/builder/__init__.py
isula/builder/client.py
isula/builder/image.py
isula/builder/manifest.py
isula/builder/system.py
isula/builder_grpc/__init__.py
isula/builder_grpc/control_pb2.py
isula/builder_grpc/control_pb2_grpc.py
isula/isulad/__init__.py
isula/isulad/client.py
isula/isulad/container.py
isula/isulad/cri.py
isula/isulad/image.py
isula/isulad/system.py
isula/isulad/volume.py
isula/isulad_grpc/__init__.py
isula/isulad_grpc/api_pb2.py
isula/isulad_grpc/api_pb2_grpc.py
isula/isulad_grpc/container_pb2.py
isula/isulad_grpc/container_pb2_grpc.py
isula/isulad_grpc/images_pb2.py
isula/isulad_grpc/images_pb2_grpc.py
isula/isulad_grpc/volumes_pb2.py
isula/isulad_grpc/volumes_pb2_grpc.py